drake/__init__.py
drake/artificialintel.py
drake/month.py
drake/numbers.py
drake/operators.py
drake/subjectpercent.py
drake/surfacearea.py
drakeparker-0.2.dist-info/License.txt
drakeparker-0.2.dist-info/METADATA
drakeparker-0.2.dist-info/WHEEL
drakeparker-0.2.dist-info/top_level.txt
drakeparker-0.2.dist-info/RECORD
